mdb_toolkit/__init__.py
mdb_toolkit/core.py
scripts/demo-kg.py
scripts/demo.py
scripts/demo_voyageai.py
mdb_toolkit-1.0.0.dist-info/LICENSE
mdb_toolkit-1.0.0.dist-info/METADATA
mdb_toolkit-1.0.0.dist-info/WHEEL
mdb_toolkit-1.0.0.dist-info/top_level.txt
mdb_toolkit-1.0.0.dist-info/RECORD
