Metadata-Version: 2.2
Name: mdb-toolkit
Version: 1.0.0
Summary: Custom MongoDB client with vector search capabilities, embeddings management, and more.
Home-page: https://github.com/ranfysvalle02/mdb_toolkit
Author: Fabian Valle
Author-email: Fabian Valle <oblivio.company@gmail.com>
License: MIT
Project-URL: homepage, https://github.com/ranfysvalle02/mdb_toolkit
Project-URL: issue_tracker, https://github.com/ranfysvalle02/mdb_toolkit/issues
Keywords: mongodb,vector search,embeddings,pymongo,custom client
Classifier: Programming Language :: Python :: 3
Classifier: Programming Language :: Python :: 3.7
Classifier: Programming Language :: Python :: 3.8
Classifier: Programming Language :: Python :: 3.9
Classifier: Programming Language :: Python :: 3.10
Classifier: License :: OSI Approved :: MIT License
Classifier: Operating System :: OS Independent
Requires-Python: >=3.7
License-File: LICENSE
Requires-Dist: pymongo>=3.11
Dynamic: author
Dynamic: home-page
Dynamic: requires-python
